odoo/addons/shopfloor_reception_mobile/README.rst
odoo/addons/shopfloor_reception_mobile/__init__.py
odoo/addons/shopfloor_reception_mobile/__manifest__.py
odoo/addons/shopfloor_reception_mobile/i18n/it.po
odoo/addons/shopfloor_reception_mobile/i18n/shopfloor_reception_mobile.pot
odoo/addons/shopfloor_reception_mobile/readme/CONTRIBUTORS.md
odoo/addons/shopfloor_reception_mobile/readme/DESCRIPTION.md
odoo/addons/shopfloor_reception_mobile/static/description/icon.png
odoo/addons/shopfloor_reception_mobile/static/description/index.html
odoo/addons/shopfloor_reception_mobile/static/src/demo/demo.reception.esm.js
odoo/addons/shopfloor_reception_mobile/static/src/scenario/reception.esm.js
odoo/addons/shopfloor_reception_mobile/static/src/scenario/reception_states.esm.js
odoo/addons/shopfloor_reception_mobile/templates/assets.xml
odoo_addon_shopfloor_reception_mobile-18.0.1.2.1.dist-info/METADATA
odoo_addon_shopfloor_reception_mobile-18.0.1.2.1.dist-info/WHEEL
odoo_addon_shopfloor_reception_mobile-18.0.1.2.1.dist-info/top_level.txt
odoo_addon_shopfloor_reception_mobile-18.0.1.2.1.dist-info/RECORD
