Metadata-Version: 2.1
Name: odoo-addon-shopfloor_reception_mobile
Version: 18.0.1.2.1
Requires-Python: >=3.10
Requires-Dist: odoo-addon-shopfloor_mobile_base==18.0.*
Requires-Dist: odoo-addon-shopfloor_reception==18.0.*
Requires-Dist: odoo==18.0.*
Summary: Scenario for receiving products
Home-page: https://github.com/OCA/stock-logistics-shopfloor
License: AGPL-3
Author: Camptocamp, Odoo Community Association (OCA)
Author-email: support@odoo-community.org
Classifier: Programming Language :: Python
Classifier: Framework :: Odoo
Classifier: Framework :: Odoo :: 18.0
Classifier: License :: OSI Approved :: GNU Affero General Public License v3
Classifier: Development Status :: 4 - Beta
